deduplicated-1.0b2.dist-info/entry_points.txt
deduplicated-1.0b2.dist-info/top_level.txt
deduplicated-1.0b2.dist-info/METADATA
deduplicated-1.0b2.dist-info/WHEEL
deduplicated-1.0b2.dist-info/RECORD
deduplicated-1.0b2.dist-info/DESCRIPTION.rst
deduplicated-1.0b2.dist-info/metadata.json
deduplicated/__main__.py
deduplicated/cmd.py
deduplicated/__init__.py
deduplicated/web/__main__.py
deduplicated/web/__init__.py
deduplicated/web/static/css/normalize.css
deduplicated/web/static/css/app.css
deduplicated/web/templates/dirlist.html
deduplicated/web/templates/dirupdate.html
deduplicated/web/templates/dirinfo.html
deduplicated/web/templates/indir.html
