Metadata-Version: 2.0
Name: deduplicated
Version: 1.0b2
Summary: Check duplicated files
Home-page: https://github.com/eduardoklosowski/deduplicated
Author: Eduardo Klosowski
Author-email: eduardo_klosowski@yahoo.com
License: MIT
Platform: UNKNOWN
Classifier: Development Status :: 4 - Beta
Classifier: Environment :: Console
Classifier: Environment :: Web Environment
Classifier: Intended Audience :: System Administrators
Classifier: License :: OSI Approved :: MIT License
Classifier: Operating System :: OS Independent
Classifier: Programming Language :: Python
Classifier: Programming Language :: Python :: 2
Classifier: Programming Language :: Python :: 2.7
Classifier: Programming Language :: Python :: 3
Classifier: Programming Language :: Python :: 3.4
Classifier: Topic :: Software Development :: Libraries :: Python Modules
Classifier: Topic :: System :: Archiving
Provides-Extra: web
Requires-Dist: Flask; extra == 'web'
